objfromconfig/__init__.py
objfromconfig/objfromconfig.py
tests/__init__.py
tests/test_objfromconfig.py
objfromconfig-0.1.0.dist-info/AUTHORS.rst
objfromconfig-0.1.0.dist-info/LICENSE
objfromconfig-0.1.0.dist-info/METADATA
objfromconfig-0.1.0.dist-info/WHEEL
objfromconfig-0.1.0.dist-info/top_level.txt
objfromconfig-0.1.0.dist-info/RECORD
