Metadata-Version: 2.1
Name: objfromconfig
Version: 0.1.0
Summary: Create objects from config data
Home-page: https://github.com/johann-petrak/objfromconfig
Author: Johann Petrak
Author-email: johann.petrak@gmail.com
License: Apache Software License 2.0
Keywords: objfromconfig
Platform: UNKNOWN
Classifier: Development Status :: 2 - Pre-Alpha
Classifier: Intended Audience :: Developers
Classifier: License :: OSI Approved :: Apache Software License
Classifier: Natural Language :: English
Classifier: Programming Language :: Python :: 3
Classifier: Programming Language :: Python :: 3.6
Classifier: Programming Language :: Python :: 3.7
Classifier: Programming Language :: Python :: 3.8
Requires-Python: >=3.6
